{
  "$schema": "https://raw.githubusercontent.com/nicehash/tauri/dev/crates/tauri-cli/schema.json",
  "productName": "牛马工资计算器",
  "version": "1.0.0",
  "identifier": "com.blingidea.niuma-calculator",
  "build": {
    "beforeDevCommand": "npm run dev",
    "devUrl": "http://localhost:1420",
    "beforeBuildCommand": "npm run build",
    "frontendDist": "../dist"
  },
  "app": {
    "windows": [
      {
        "title": "牛马工资计算器",
        "label": "main",
        "width": 220,
        "height": 420,
        "resizable": false,
        "decorations": false,
        "transparent": true,
        "alwaysOnTop": true,
        "skipTaskbar": false,
        "center": false,
        "x": 100,
        "y": 100
      }
    ],
    "security": {
      "csp": null
    }
  },
  "bundle": {
    "active": true,
    "targets": "all",
    "icon": [
      "icons/fish.ico"
    ]
  }
}
